aliyunsdkcloudapi/__init__.py
aliyunsdkcloudapi/endpoint.py
aliyunsdkcloudapi/request/__init__.py
aliyunsdkcloudapi/request/v20160714/AbolishApiRequest.py
aliyunsdkcloudapi/request/v20160714/AddAccessControlListEntryRequest.py
aliyunsdkcloudapi/request/v20160714/AddIpControlPolicyItemRequest.py
aliyunsdkcloudapi/request/v20160714/AddTrafficSpecialControlRequest.py
aliyunsdkcloudapi/request/v20160714/AttachApiProductRequest.py
aliyunsdkcloudapi/request/v20160714/AttachPluginRequest.py
aliyunsdkcloudapi/request/v20160714/BatchAbolishApisRequest.py
aliyunsdkcloudapi/request/v20160714/BatchDeployApisRequest.py
aliyunsdkcloudapi/request/v20160714/CreateAccessControlListRequest.py
aliyunsdkcloudapi/request/v20160714/CreateApiGroupRequest.py
aliyunsdkcloudapi/request/v20160714/CreateApiRequest.py
aliyunsdkcloudapi/request/v20160714/CreateApiStageVariableRequest.py
aliyunsdkcloudapi/request/v20160714/CreateAppRequest.py
aliyunsdkcloudapi/request/v20160714/CreateBackendModelRequest.py
aliyunsdkcloudapi/request/v20160714/CreateBackendRequest.py
aliyunsdkcloudapi/request/v20160714/CreateDatasetItemRequest.py
aliyunsdkcloudapi/request/v20160714/CreateDatasetRequest.py
aliyunsdkcloudapi/request/v20160714/CreateInstanceRequest.py
aliyunsdkcloudapi/request/v20160714/CreateIntranetDomainRequest.py
aliyunsdkcloudapi/request/v20160714/CreateIpControlRequest.py
aliyunsdkcloudapi/request/v20160714/CreateLogConfigRequest.py
aliyunsdkcloudapi/request/v20160714/CreateModelRequest.py
aliyunsdkcloudapi/request/v20160714/CreateMonitorGroupRequest.py
aliyunsdkcloudapi/request/v20160714/CreatePluginRequest.py
aliyunsdkcloudapi/request/v20160714/CreateSignatureRequest.py
aliyunsdkcloudapi/request/v20160714/CreateTrafficControlRequest.py
aliyunsdkcloudapi/request/v20160714/DeleteAccessControlListRequest.py
aliyunsdkcloudapi/request/v20160714/DeleteAllTrafficSpecialControlRequest.py
aliyunsdkcloudapi/request/v20160714/DeleteApiGroupRequest.py
aliyun_python_sdk_cloudapi-1.0.4.dist-info/LICENSE
aliyun_python_sdk_cloudapi-1.0.4.dist-info/METADATA
aliyun_python_sdk_cloudapi-1.0.4.dist-info/WHEEL
aliyun_python_sdk_cloudapi-1.0.4.dist-info/top_level.txt
aliyun_python_sdk_cloudapi-1.0.4.dist-info/RECORD
